[
  {
    "line": 2,
    "elements": [
      {
        "line": 4,
        "name": "",
        "description": "",
        "type": "background",
        "keyword": "Background",
        "steps": [
          {
            "result": {
              "duration": 805545200,
              "status": "passed"
            },
            "line": 5,
            "name": "User is on the techfios login page",
            "match": {
              "location": "BankAndCashStepDefination.user_is_on_the_techfios_login_page()"
            },
            "keyword": "Given "
          }
        ]
      },
      {
        "before": [
          {
            "result": {
              "duration": 3114806800,
              "status": "passed"
            },
            "match": {
              "location": "BankAndCashStepDefination.berforeRun()"
            }
          }
        ],
        "line": 27,
        "name": "1 User should be able to login with valid credentials and open a new account",
        "description": "",
        "id": "techfios-bank-and-cash-new-account-functionality;1-user-should-be-able-to-login-with-valid-credentials-and-open-a-new-account;;2",
        "type": "scenario",
        "keyword": "Scenario Outline",
        "steps": [
          {
            "result": {
              "duration": 2266583000,
              "status": "passed"
            },
            "line": 9,
            "name": "User enters the username as\"demo@techfios.com\"",
            "match": {
              "arguments": [
                {
                  "val": "demo@techfios.com",
                  "offset": 28
                }
              ],
              "location": "BankAndCashStepDefination.User_enters_the_username_as(String)"
            },
            "matchedColumns": [
              0
            ],
            "keyword": "When "
          },
          {
            "result": {
              "duration": 1202750700,
              "status": "passed"
            },
            "line": 10,
            "name": "User enters the password as\"abc123\"",
            "match": {
              "arguments": [
                {
                  "val": "abc123",
                  "offset": 28
                }
              ],
              "location": "BankAndCashStepDefination.user_enters_the_password_as(String)"
            },
            "matchedColumns": [
              1
            ],
            "keyword": "When "
          },
          {
            "result": {
              "duration": 3088874600,
              "status": "passed"
            },
            "line": 11,
            "name": "User clicks on signin\"\u003csignin\u003e\"",
            "match": {
              "arguments": [
                {
                  "val": "\u003csignin\u003e",
                  "offset": 22
                }
              ],
              "location": "BankAndCashStepDefination.user_clicks_on_signin(String)"
            },
            "keyword": "And "
          },
          {
            "result": {
              "duration": 128260800,
              "status": "passed"
            },
            "line": 12,
            "name": "User should land on Dashboard page",
            "match": {
              "location": "BankAndCashStepDefination.user_should_land_on_Dashboard_page()"
            },
            "keyword": "Then "
          },
          {
            "result": {
              "duration": 1340826100,
              "status": "passed"
            },
            "line": 13,
            "name": "User clicks on bankCash",
            "match": {
              "location": "BankAndCashStepDefination.user_clicks_on_bankCash()"
            },
            "keyword": "And "
          },
          {
            "result": {
              "duration": 1559656500,
              "status": "passed"
            },
            "line": 14,
            "name": "User clicks on newAccount",
            "match": {
              "location": "BankAndCashStepDefination.user_clicks_on_newAccount()"
            },
            "keyword": "And "
          },
          {
            "result": {
              "duration": 1153887200,
              "status": "passed"
            },
            "line": 15,
            "name": "User enters\"Ekta_Cucumber_Test\"in accounts page",
            "match": {
              "arguments": [
                {
                  "val": "Ekta_Cucumber_Test",
                  "offset": 12
                }
              ],
              "location": "BankAndCashStepDefination.user_enters_in_accounts_page(String)"
            },
            "matchedColumns": [
              2
            ],
            "keyword": "And "
          },
          {
            "result": {
              "duration": 1201247700,
              "status": "passed"
            },
            "line": 16,
            "name": "User enters description as\"Savings Account\"in accounts page",
            "match": {
              "arguments": [
                {
                  "val": "Savings Account",
                  "offset": 27
                }
              ],
              "location": "BankAndCashStepDefination.user_enters_description_as_in_accounts_page(String)"
            },
            "matchedColumns": [
              3
            ],
            "keyword": "And "
          },
          {
            "result": {
              "duration": 1187114800,
              "status": "passed"
            },
            "line": 17,
            "name": "User enters initialBalance as\"20000\"in accounts page",
            "match": {
              "arguments": [
                {
                  "val": "20000",
                  "offset": 30
                }
              ],
              "location": "BankAndCashStepDefination.user_enters_initialBalance_as_in_accounts_page(String)"
            },
            "matchedColumns": [
              4
            ],
            "keyword": "And "
          },
          {
            "result": {
              "duration": 1237087900,
              "status": "passed"
            },
            "line": 18,
            "name": "User enters accountNumber as\"887654332\"in accounts page",
            "match": {
              "arguments": [
                {
                  "val": "887654332",
                  "offset": 29
                }
              ],
              "location": "BankAndCashStepDefination.user_enters_accountNumber_as_in_accounts_page(String)"
            },
            "matchedColumns": [
              5
            ],
            "keyword": "And "
          },
          {
            "result": {
              "duration": 1262755100,
              "status": "passed"
            },
            "line": 19,
            "name": "User enters contactPerson as\"Nipun\"in accounts page",
            "match": {
              "arguments": [
                {
                  "val": "Nipun",
                  "offset": 29
                }
              ],
              "location": "BankAndCashStepDefination.user_enters_contactPerson_as_in_accounts_page(String)"
            },
            "matchedColumns": [
              6
            ],
            "keyword": "And "
          },
          {
            "result": {
              "duration": 1198008700,
              "status": "passed"
            },
            "line": 20,
            "name": "User enters contactPhone as\"2354685432\"in accounts page",
            "match": {
              "arguments": [
                {
                  "val": "2354685432",
                  "offset": 28
                }
              ],
              "location": "BankAndCashStepDefination.user_enters_contactPhone_as_in_accounts_page(String)"
            },
            "matchedColumns": [
              7
            ],
            "keyword": "And "
          },
          {
            "result": {
              "duration": 1353411800,
              "status": "passed"
            },
            "line": 21,
            "name": "User enters internetBankingURL as\"https://techfios.com/billing/?ng\u003daccounts/list/\"in accounts page",
            "match": {
              "arguments": [
                {
                  "val": "https://techfios.com/billing/?ng\u003daccounts/list/",
                  "offset": 34
                }
              ],
              "location": "BankAndCashStepDefination.user_enters_internetBankingURL_as_in_accounts_page(String)"
            },
            "matchedColumns": [
              8
            ],
            "keyword": "And "
          },
          {
            "result": {
              "duration": 1112369500,
              "status": "passed"
            },
            "line": 22,
            "name": "User clicks on submit",
            "match": {
              "location": "BankAndCashStepDefination.user_clicks_on_submit()"
            },
            "keyword": "And "
          },
          {
            "result": {
              "duration": 5882300,
              "status": "passed"
            },
            "line": 23,
            "name": "User should be able to validate account created successfully",
            "match": {
              "location": "BankAndCashStepDefination.user_should_be_able_to_validate_account_created_successfully()"
            },
            "keyword": "Then "
          }
        ],
        "tags": [
          {
            "line": 1,
            "name": "@BankandCashFeature"
          }
        ]
      }
    ],
    "name": "Techfios bank and cash New Account Functionality",
    "description": "",
    "id": "techfios-bank-and-cash-new-account-functionality",
    "keyword": "Feature",
    "uri": "features/BankAndCash.feature",
    "tags": [
      {
        "line": 1,
        "name": "@BankandCashFeature"
      }
    ]
  }
]